macuiauto/AXCallbacks.py
macuiauto/AXClasses.py
macuiauto/__init__.py
macuiauto/_a11y.py
macuiauto/_converter.py
macuiauto/_macos.py
macuiauto/_notification.py
macuiauto/errors.py
macuiauto/_mixin/__init__.py
macuiauto/_mixin/_input.py
macuiauto/_mixin/_wait.py
macuiauto-3.2.1.dist-info/WHEEL
macuiauto-3.2.1.dist-info/METADATA
macuiauto-3.2.1.dist-info/RECORD
