Metadata-Version: 2.3
Name: macuiauto
Version: 3.2.1
Summary: Automated Testing on macOS
Home-page: https://github.com/GenoChen/mac-ui-automation
Author: Geno Chen
Author-email: geno.chenjiannan@gmail.com
Classifier: Development Status :: 5 - Production/Stable
Classifier: Environment :: MacOS X
Classifier: Environment :: MacOS X :: Cocoa
Classifier: Intended Audience :: Developers
Classifier: License :: OSI Approved :: GNU General Public License v2 (GPLv2)
Classifier: Operating System :: MacOS
Classifier: Operating System :: MacOS :: MacOS X
Classifier: Programming Language :: Objective C
Classifier: Programming Language :: Python
Classifier: Programming Language :: Python :: 3
Classifier: Programming Language :: Python :: 3.8
Classifier: Programming Language :: Python :: 3.9
Classifier: Programming Language :: Python :: 3.10
Classifier: Programming Language :: Python :: 3.11
Classifier: Topic :: Software Development :: Libraries
Classifier: Topic :: Software Development :: Libraries :: Python Modules
Classifier: Topic :: Software Development :: Quality Assurance
Classifier: Topic :: Software Development :: Testing
Classifier: Topic :: Software Development :: User Interfaces
Requires-Dist: pyobjc-core>=3.0.4
Requires-Dist: pyobjc-framework-Cocoa>=3.0.4
Requires-Dist: pyobjc-framework-Quartz>=3.0.4
Requires-Dist: pyobjc-framework-ApplicationServices>=3.0.4
Requires-Dist: pyobjc-framework-CoreText>=3.0.4
Requires-Dist: pynput>=1.7.7
